main.py
src/__init__.py
src/gui/__init__.py
src/gui/helpers.py
src/gui/interface.py
src/gui/neighborhood_list.py
src/gui/db/models.py
mgtron_gui-2.15.5.dist-info/METADATA
mgtron_gui-2.15.5.dist-info/WHEEL
mgtron_gui-2.15.5.dist-info/licenses/LICENSE.rst
mgtron_gui-2.15.5.dist-info/RECORD
