Metadata-Version: 2.1
Name: mgtron_gui
Version: 2.15.5
Summary: Package for MGTron GUI, a user interface for signal generation
Project-URL: Source, https://github.com/cellantenna/mg_tron
Author-email: Christerpher Hunter <chunter@cellantenna.com>
License-File: LICENSE.rst
Classifier: License :: Other/Proprietary License
Classifier: Operating System :: POSIX :: Linux
Classifier: Programming Language :: Python :: 3
Requires-Python: >=3.10
